cell_filter/__init__.py
cell_filter/__main__.py
cell_filter/_dirichlet_multinomial.py
cell_filter/_multinomial.py
cell_filter/_sgt.py
cell_filter/_utils.py
cell_filter/lib.py
cell_filter/py.typed
cell_filter-0.1.2.dist-info/METADATA
cell_filter-0.1.2.dist-info/WHEEL
cell_filter-0.1.2.dist-info/entry_points.txt
cell_filter-0.1.2.dist-info/licenses/LICENSE
cell_filter-0.1.2.dist-info/RECORD
