Metadata-Version: 2.4
Name: cell-filter
Version: 0.1.2
Summary: A python implementation of the EmptyDrops algorithm
Author-email: noam teyssier <22600644+noamteyssier@users.noreply.github.com>
License-Expression: MIT
License-File: LICENSE
Requires-Python: >=3.13
Requires-Dist: anndata>=0.12.1
Requires-Dist: numba>=0.61.2
Requires-Dist: scipy>=1.16.1
Requires-Dist: tqdm>=4.67.1
Requires-Dist: typer>=0.16.0
